{
    "CarBrain": {
        "checkpoints": [
            {
                "steps": 499958,
                "file_path": "results\\base_7\\CarBrain\\CarBrain-499958.onnx",
                "reward": 786.1342934370041,
                "creation_time": 1782313594.2142777,
                "auxillary_file_paths": [
                    "results\\base_7\\CarBrain\\CarBrain-499958.pt"
                ]
            },
            {
                "steps": 500086,
                "file_path": "results\\base_7\\CarBrain\\CarBrain-500086.onnx",
                "reward": 786.1342934370041,
                "creation_time": 1782313594.3237221,
                "auxillary_file_paths": [
                    "results\\base_7\\CarBrain\\CarBrain-500086.pt"
                ]
            }
        ],
        "final_checkpoint": {
            "steps": 500086,
            "file_path": "results\\base_7\\CarBrain.onnx",
            "reward": 786.1342934370041,
            "creation_time": 1782313594.3237221,
            "auxillary_file_paths": [
                "results\\base_7\\CarBrain\\CarBrain-500086.pt"
            ]
        }
    },
    "metadata": {
        "stats_format_version": "0.3.0",
        "mlagents_version": "1.1.0",
        "torch_version": "2.2.1+cu121"
    }
}